flarenet/__init__.py
flarenet/_activation.py
flarenet/_attention.py
flarenet/_combine.py
flarenet/_conv.py
flarenet/_linear.py
flarenet/_norm.py
flarenet/_utils.py
flarenet-0.3.15.dist-info/METADATA
flarenet-0.3.15.dist-info/WHEEL
flarenet-0.3.15.dist-info/top_level.txt
flarenet-0.3.15.dist-info/RECORD
