Metadata-Version: 2.1
Name: flarenet
Version: 0.3.15
Summary: Common neural network modules and utilities based on flarejax.
Home-page: https://github.com/pwolle/flarenet
Author: Paul Wollenhaupt
Author-email: paul.wollenhaupt@gmail.com
Requires-Python: >=3.10
Requires-Dist: flarejax
Requires-Dist: jaxtyping
Requires-Dist: oryx
